pocpy/__init__.py
pocpy/logpolar_opencv2.py
pocpy/logpolar_opencv3.py
pocpy/poc.py
pocpy-0.2.0.dist-info/LICENSE
pocpy-0.2.0.dist-info/METADATA
pocpy-0.2.0.dist-info/WHEEL
pocpy-0.2.0.dist-info/top_level.txt
pocpy-0.2.0.dist-info/RECORD
